sisl/CMakeLists.txt
sisl/__init__.py
sisl/__main__.py
sisl/_array.py
sisl/_category.py
sisl/_common.py
sisl/_debug_info.py
sisl/_dispatch_class.py
sisl/_dispatcher.py
sisl/_environ.py
sisl/_help.py
sisl/_indices.cpython-313-x86_64-linux-musl.so
sisl/_indices.pxd
sisl/_indices.pyx
sisl/_internal.py
sisl/_lazy_viz.py
sisl/_math_small.cpython-313-x86_64-linux-musl.so
sisl/_math_small.pyx
sisl/_namedindex.py
sisl/_nodify.py
sisl/_sparse_grid.py
sisl/_sparse_grid_ops.cpython-313-x86_64-linux-musl.so
sisl/_sparse_grid_ops.py
sisl/_ufuncs.py
sisl/_version.py
sisl/conftest.py
sisl/constant.py
sisl/messages.py
sisl/_core/CMakeLists.txt
sisl/_core/__init__.py
sisl/_core/_dtypes.cpython-313-x86_64-linux-musl.so
sisl/_core/_dtypes.pxd
sisl/_core/_dtypes.pyx
sisl/_core/_lattice.cpython-313-x86_64-linux-musl.so
sisl/_core/_lattice.pyx
sisl/_core/_sparse.cpython-313-x86_64-linux-musl.so
sisl/_core/_sparse.pxd
sisl/_core/_sparse.pyx
sisl/_core/_ufuncs_atom.py
sisl/_core/_ufuncs_geometry.py
sisl/_core/_ufuncs_grid.py
sisl/_core/_ufuncs_lattice.py
sisl/_core/_ufuncs_orbital.py
sisl/_core/_ufuncs_sparse.py
sisl/_core/_ufuncs_sparse_geometry.py
sisl/_core/atom.py
sisl/_core/geometry.py
sisl/_core/grid.py
sisl/_core/lattice.py
sisl/_core/oplist.py
sisl/_core/orbital.py
sisl/_core/periodictable.py
sisl/_core/quaternion.py
sisl/_core/sparse.py
sisl/_core/sparse_geometry.py
sisl/_core/tests/__init__.py
sisl/_core/tests/test_atom.py
sisl/_core/tests/test_atoms.py
sisl/_core/tests/test_geometry.py
sisl/_core/tests/test_geometry_return.py
sisl/_core/tests/test_grid.py
sisl/_core/tests/test_lattice.py
sisl/_core/tests/test_oplist.py
sisl/_core/tests/test_orbital.py
sisl/_core/tests/test_quaternion.py
sisl/_core/tests/test_sgeom.py
sisl/_core/tests/test_sgrid.py
sisl/_core/tests/test_sparse.py
sisl/_core/tests/test_sparse_geometry.py
sisl/_core/tests/test_sparse_orbital.py
sisl/_lib/_argparse.py
sisl/_lib/_docscrape.py
sisl-0.16.2.dist-info/METADATA
sisl-0.16.2.dist-info/WHEEL
sisl-0.16.2.dist-info/entry_points.txt
sisl-0.16.2.dist-info/RECORD
sisl-0.16.2.dist-info/licenses/LICENSE
