Metadata-Version: 2.2
Name: sisl
Version: 0.16.2
Summary: Manipulation and post-processing of DFT output and creating tight-binding models for NEGF transport
Keywords: tight-binding,DFT,LCAO,NEGF,physics,bandstructure,solid-state
Author: Pol Febrer
Author-Email: Nick Papior <nickpapior@gmail.com>
Maintainer: sisl developers
License: MPL-2.0
Classifier: Development Status :: 5 - Production/Stable
Classifier: Environment :: Console
Classifier: Intended Audience :: Science/Research
Classifier: Intended Audience :: Developers
Classifier: License :: OSI Approved :: Mozilla Public License 2.0 (MPL 2.0)
Classifier: Programming Language :: C
Classifier: Programming Language :: Fortran
Classifier: Programming Language :: Python
Classifier: Programming Language :: Python :: 3.9
Classifier: Programming Language :: Python :: 3.10
Classifier: Programming Language :: Python :: 3.11
Classifier: Programming Language :: Python :: 3.12
Classifier: Programming Language :: Python :: 3.13
Classifier: Programming Language :: Python :: 3 :: Only
Classifier: Programming Language :: Python :: Implementation :: CPython
Classifier: Topic :: Software Development
Classifier: Topic :: Scientific/Engineering
Classifier: Topic :: Scientific/Engineering :: Physics
Classifier: Operating System :: OS Independent
Project-URL: Homepage, https://zerothi.github.io/sisl
Project-URL: Releases, https://github.com/zerothi/sisl/releases
Project-URL: Documentation, https://zerothi.github.io/sisl
Project-URL: Source, https://github.com/zerothi/sisl
Project-URL: Tracker, https://github.com/zerothi/sisl/issues
Project-URL: Discussions, https://github.com/zerothi/sisl/discussions
Project-URL: Changelog, https://zerothi.github.io/sisl/release.html
Project-URL: Chat, https://discord.gg/5XnFXFdkv2
Requires-Python: >=3.9
Requires-Dist: numpy>=1.21
Requires-Dist: scipy>=1.6
Requires-Dist: pyparsing>=2.2.1
Requires-Dist: xarray>=0.21
Provides-Extra: analysis
Requires-Dist: netCDF4; extra == "analysis"
Requires-Dist: tqdm>=4.36.0; extra == "analysis"
Provides-Extra: viz
Requires-Dist: nodify; extra == "viz"
Requires-Dist: netCDF4; extra == "viz"
Requires-Dist: dill>=0.3.2; extra == "viz"
Requires-Dist: pathos; extra == "viz"
Requires-Dist: scikit-image; extra == "viz"
Requires-Dist: plotly; extra == "viz"
Requires-Dist: matplotlib; extra == "viz"
Requires-Dist: ase; extra == "viz"
Provides-Extra: viz-plotly
Requires-Dist: nodify; extra == "viz-plotly"
Requires-Dist: netCDF4; extra == "viz-plotly"
Requires-Dist: dill>=0.3.2; extra == "viz-plotly"
Requires-Dist: pathos; extra == "viz-plotly"
Requires-Dist: scikit-image; extra == "viz-plotly"
Requires-Dist: plotly; extra == "viz-plotly"
Provides-Extra: viz-matplotlib
Requires-Dist: nodify; extra == "viz-matplotlib"
Requires-Dist: netCDF4; extra == "viz-matplotlib"
Requires-Dist: dill>=0.3.2; extra == "viz-matplotlib"
Requires-Dist: pathos; extra == "viz-matplotlib"
Requires-Dist: scikit-image; extra == "viz-matplotlib"
Requires-Dist: matplotlib; extra == "viz-matplotlib"
Provides-Extra: viz-blender
Requires-Dist: nodify; extra == "viz-blender"
Requires-Dist: netCDF4; extra == "viz-blender"
Requires-Dist: dill>=0.3.2; extra == "viz-blender"
Requires-Dist: pathos; extra == "viz-blender"
Requires-Dist: scikit-image; extra == "viz-blender"
Provides-Extra: viz-ase
Requires-Dist: netCDF4; extra == "viz-ase"
Requires-Dist: dill>=0.3.2; extra == "viz-ase"
Requires-Dist: pathos; extra == "viz-ase"
Requires-Dist: scikit-image; extra == "viz-ase"
Requires-Dist: ase; extra == "viz-ase"
Provides-Extra: test
Requires-Dist: pytest>=7; extra == "test"
Requires-Dist: coverage[toml]; extra == "test"
Requires-Dist: pytest-cov; extra == "test"
Requires-Dist: pytest-env; extra == "test"
Requires-Dist: pytest-faulthandler; extra == "test"
Provides-Extra: docs
Requires-Dist: sphinx<8; extra == "docs"
Requires-Dist: plotly<6; extra == "docs"
Requires-Dist: nbsphinx; extra == "docs"
Requires-Dist: sphinx-rtd-theme; extra == "docs"
Requires-Dist: sphinx-design; extra == "docs"
Requires-Dist: sphinx-gallery; extra == "docs"
Requires-Dist: sphinx-copybutton; extra == "docs"
Requires-Dist: sphinx-togglebutton; extra == "docs"
Requires-Dist: sphinx-inline-tabs; extra == "docs"
Requires-Dist: sphinxcontrib-bibtex; extra == "docs"
Requires-Dist: sphinxext-rediraffe; extra == "docs"
Requires-Dist: importlib-metadata; extra == "docs"
Requires-Dist: ipykernel; extra == "docs"
Requires-Dist: ipywidgets; extra == "docs"
Requires-Dist: jupyterlab-widgets; extra == "docs"
Requires-Dist: kaleido; extra == "docs"
Requires-Dist: pytz; extra == "docs"
Requires-Dist: networkx; extra == "docs"
Requires-Dist: pyvis; extra == "docs"
Requires-Dist: pybtex; extra == "docs"
Requires-Dist: pandoc; extra == "docs"
